Workbook

Sheet dummy_data
A1: UKPRN | B1: Name | C1: Country | D1: Ofs_Tariff_1920 | E1: TEF_1819 | F1: Student numbers | G1: Total Expenditure
A2: 10007814 | B2: =_xlfn.XLOOKUP($A2, PUBLISHED_Provider_Spine_202208!$A$2:$A$620, PUBLISHED_Provider_Spine_202208!$C$2:$C$620) -> Cardiff University | C2: =_xlfn.XLOOKUP($A2, PUBLISHED_Provider_Spine_202208!$A$2:$A$620, PUBLISHED_Provider_Spine_202208!$F$2:$F$620) -> Wales | D2: #N/A | E2: =_xlfn.XLOOKUP($A2, PUBLISHED_Provider_Spine_202208!$A$2:$A$620, PUBLISHED_Provider_Spine_202208!$AG$2:$AG$620) -> Silver | F2: =_xlfn.XLOOKUP(A2, Students!$A$19:$A$300, Students!$G$19:$G$300) -> 33510 | G2: =_xlfn.XLOOKUP($A2, Finance!$A$18:$A$291, Finance!$P$18:$P$291) -> 573201
A3: 10007790 | B3: =_xlfn.XLOOKUP(A3, PUBLISHED_Provider_Spine_202208!$A$2:$A$620, PUBLISHED_Provider_Spine_202208!$C$2:$C$620) -> The University of Edinburgh | C3: =_xlfn.XLOOKUP($A3, PUBLISHED_Provider_Spine_202208!$A$2:$A$620, PUBLISHED_Provider_Spine_202208!$F$2:$F$620) -> Scotland | D3: #N/A | E3: =_xlfn.XLOOKUP($A3, PUBLISHED_Provider_Spine_202208!$A$2:$A$620, PUBLISHED_Provider_Spine_202208!$AG$2:$AG$620) -> No TEF | F3: =_xlfn.XLOOKUP(A3, Students!$A$19:$A$300, Students!$G$19:$G$300) -> 37830 | G3: =_xlfn.XLOOKUP($A3, Finance!$A$18:$A$291, Finance!$P$18:$P$291) -> 1060066
A4: 10007794 | B4: =_xlfn.XLOOKUP(A4, PUBLISHED_Provider_Spine_202208!$A$2:$A$620, PUBLISHED_Provider_Spine_202208!$C$2:$C$620) -> The University of Glasgow | C4: =_xlfn.XLOOKUP($A4, PUBLISHED_Provider_Spine_202208!$A$2:$A$620, PUBLISHED_Provider_Spine_202208!$F$2:$F$620) -> Scotland | D4: #N/A | E4: =_xlfn.XLOOKUP($A4, PUBLISHED_Provider_Spine_202208!$A$2:$A$620, PUBLISHED_Provider_Spine_202208!$AG$2:$AG$620) -> No TEF | F4: =_xlfn.XLOOKUP(A4, Students!$A$19:$A$300, Students!$G$19:$G$300) -> 37145 | G4: =_xlfn.XLOOKUP($A4, Finance!$A$18:$A$291, Finance!$P$18:$P$291) -> 695820
A5: 10000291 | B5: =_xlfn.XLOOKUP(A5, PUBLISHED_Provider_Spine_202208!$A$2:$A$620, PUBLISHED_Provider_Spine_202208!$C$2:$C$620) -> Anglia Ruskin University Higher Education Corporation | C5: =_xlfn.XLOOKUP($A5, PUBLISHED_Provider_Spine_202208!$A$2:$A$620, PUBLISHED_Provider_Spine_202208!$F$2:$F$620) -> England | D5: =_xlfn.XLOOKUP($A5, PUBLISHED_Provider_Spine_202208!$A$2:$A$620, PUBLISHED_Provider_Spine_202208!$AD$2:$AD$620) -> HEIs with low scores | E5: =_xlfn.XLOOKUP($A5, PUBLISHED_Provider_Spine_202208!$A$2:$A$620, PUBLISHED_Provider_Spine_202208!$AG$2:$AG$620) -> Silver | F5: =_xlfn.XLOOKUP(A5, Students!$A$19:$A$300, Students!$G$19:$G$300) -> 32180 | G5: =_xlfn.XLOOKUP($A5, Finance!$A$18:$A$291, Finance!$P$18:$P$291) -> 270231
A6: 10008640 | B6: =_xlfn.XLOOKUP(A6, PUBLISHED_Provider_Spine_202208!$A$2:$A$620, PUBLISHED_Provider_Spine_202208!$C$2:$C$620) -> Falmouth University | C6: =_xlfn.XLOOKUP($A6, PUBLISHED_Provider_Spine_202208!$A$2:$A$620, PUBLISHED_Provider_Spine_202208!$F$2:$F$620) -> England | D6: =_xlfn.XLOOKUP($A6, PUBLISHED_Provider_Spine_202208!$A$2:$A$620, PUBLISHED_Provider_Spine_202208!$AD$2:$AD$620) -> Specialist HEI | E6: =_xlfn.XLOOKUP($A6, PUBLISHED_Provider_Spine_202208!$A$2:$A$620, PUBLISHED_Provider_Spine_202208!$AG$2:$AG$620) -> Gold | F6: =_xlfn.XLOOKUP(A6, Students!$A$19:$A$300, Students!$G$19:$G$300) -> 6170 | G6: =_xlfn.XLOOKUP($A6, Finance!$A$18:$A$291, Finance!$P$18:$P$291) -> 64303
A7: 10007760 | B7: =_xlfn.XLOOKUP(A7, PUBLISHED_Provider_Spine_202208!$A$2:$A$620, PUBLISHED_Provider_Spine_202208!$C$2:$C$620) -> Birkbeck College | C7: =_xlfn.XLOOKUP($A7, PUBLISHED_Provider_Spine_202208!$A$2:$A$620, PUBLISHED_Provider_Spine_202208!$F$2:$F$620) -> England | D7: =_xlfn.XLOOKUP($A7, PUBLISHED_Provider_Spine_202208!$A$2:$A$620, PUBLISHED_Provider_Spine_202208!$AD$2:$AD$620) -> Specialist HEI | E7: =_xlfn.XLOOKUP($A7, PUBLISHED_Provider_Spine_202208!$A$2:$A$620, PUBLISHED_Provider_Spine_202208!$AG$2:$AG$620) -> Silver | F7: =_xlfn.XLOOKUP(A7, Students!$A$19:$A$300, Students!$G$19:$G$300) -> 12070 | G7: =_xlfn.XLOOKUP($A7, Finance!$A$18:$A$291, Finance!$P$18:$P$291) -> 106783
A8: 10007792 | B8: =_xlfn.XLOOKUP(A8, PUBLISHED_Provider_Spine_202208!$A$2:$A$620, PUBLISHED_Provider_Spine_202208!$C$2:$C$620) -> University of Exeter | C8: =_xlfn.XLOOKUP($A8, PUBLISHED_Provider_Spine_202208!$A$2:$A$620, PUBLISHED_Provider_Spine_202208!$F$2:$F$620) -> England | D8: =_xlfn.XLOOKUP($A8, PUBLISHED_Provider_Spine_202208!$A$2:$A$620, PUBLISHED_Provider_Spine_202208!$AD$2:$AD$620) -> HEIs with high scores | E8: =_xlfn.XLOOKUP($A8, PUBLISHED_Provider_Spine_202208!$A$2:$A$620, PUBLISHED_Provider_Spine_202208!$AG$2:$AG$620) -> Gold | F8: =_xlfn.XLOOKUP(A8, Students!$A$19:$A$300, Students!$G$19:$G$300) -> 30250 | G8: =_xlfn.XLOOKUP($A8, Finance!$A$18:$A$291, Finance!$P$18:$P$291) -> 512915
A9: 10007799 | B9: =_xlfn.XLOOKUP(A9, PUBLISHED_Provider_Spine_202208!$A$2:$A$620, PUBLISHED_Provider_Spine_202208!$C$2:$C$620) -> University of Newcastle upon Tyne | C9: =_xlfn.XLOOKUP($A9, PUBLISHED_Provider_Spine_202208!$A$2:$A$620, PUBLISHED_Provider_Spine_202208!$F$2:$F$620) -> England | D9: =_xlfn.XLOOKUP($A9, PUBLISHED_Provider_Spine_202208!$A$2:$A$620, PUBLISHED_Provider_Spine_202208!$AD$2:$AD$620) -> HEIs with high scores | E9: =_xlfn.XLOOKUP($A9, PUBLISHED_Provider_Spine_202208!$A$2:$A$620, PUBLISHED_Provider_Spine_202208!$AG$2:$AG$620) -> Gold | F9: =_xlfn.XLOOKUP(A9, Students!$A$19:$A$300, Students!$G$19:$G$300) -> 27775 | G9: =_xlfn.XLOOKUP($A9, Finance!$A$18:$A$291, Finance!$P$18:$P$291) -> 530603
A10: 10007154 | B10: =_xlfn.XLOOKUP(A10, PUBLISHED_Provider_Spine_202208!$A$2:$A$620, PUBLISHED_Provider_Spine_202208!$C$2:$C$620) -> University of Nottingham, the | C10: =_xlfn.XLOOKUP($A10, PUBLISHED_Provider_Spine_202208!$A$2:$A$620, PUBLISHED_Provider_Spine_202208!$F$2:$F$620) -> England | D10: =_xlfn.XLOOKUP($A10, PUBLISHED_Provider_Spine_202208!$A$2:$A$620, PUBLISHED_Provider_Spine_202208!$AD$2:$AD$620) -> HEIs with high scores | E10: =_xlfn.XLOOKUP($A10, PUBLISHED_Provider_Spine_202208!$A$2:$A$620, PUBLISHED_Provider_Spine_202208!$AG$2:$AG$620) -> Gold | F10: =_xlfn.XLOOKUP(A10, Students!$A$19:$A$300, Students!$G$19:$G$300) -> 35785 | G10: =_xlfn.XLOOKUP($A10, Finance!$A$18:$A$291, Finance!$P$18:$P$291) -> 683714

Sheet PUBLISHED_Provider_Spine_202208
A1: UKPRN | B1: INSTID | C1: Name | D1: Short_name | E1: UCAS_code | F1: Country | G1: Region | H1: Postcode | I1: Longitude | J1: Latitude | K1: LTLA_code | L1: LTLA_name | M1: ITL_code | N1: ITL_name | O1: Constituency | P1: Town_or_City | Q1: OfS_register | R1: HESA_FR | S1: HESA_Staff | T1: HESA_SR | U1: Grad_outcomes | V1: Unistats | W1: SLC | X1: UCAS | Y1: Prov_type | Z1: Old_Prov_type | AA1: Reg_cat | AB1: T_grant_2223 | AC1: HCSF_2223 | AD1: Ofs_Tariff_1920 | AE1: WP_UCAS_Tariff | AF1: TRAC_1819 | AG1: TEF_1819 | AH1: Mission_groups | AI1: New_in_update
A2: 10007849 | B2: 95 | C2: Abertay University | D2: Abertay | E2: A30 | F2: Scotland | G2: Scotland | H2: DD1 1HG | I2: -2.974299 | J2: 56.463117 | K2: S12000042 | L2: Dundee City | M2: S30000049 | N2: Dundee City | O2: Dundee West | P2: NA | Q2: 0 | R2: 1 | S2: 1 | T2: 1 | U2: 0 | V2: 0 | W2: 1 | X2: 1 | Y2: None | Z2: HEI | AA2: Not OfS | AB2: NA | AC2: NA | AD2: No tariff | AE2: High | AF2: C | AG2: Silver | AH2: MillionPlus, GuildHE | AI2: 0
A3: 10007856 | B3: 177 | C3: Aberystwyth University | D3: Aberystwyth | E3: A40 | F3: Wales | G3: Wales | H3: SY23 2AX | I3: -4.043584 | J3: 52.403464 | K3: W06000008 | L3: Ceredigion | M3: W06000008 | N3: Ceredigion | O3: Ceredigion | Q3: 0 | R3: 1 | S3: 1 | T3: 1 | U3: 0 | V3: 0 | W3: 1 | X3: 1 | Y3: None | Z3: HEI | AA3: Not OfS | AB3: NA | AC3: NA | AD3: No tariff | AE3: Low | AF3: B | AG3: Gold | AH3: None | AI3: 0
A4: 10019746 | B4: 231 | C4: ABI College Limited | D4: ABI | E4: Not UCAS | F4: England | G4: London | H4: W3 9NW | I4: -0.271846 | J4: 51.507759 | K4: E09000009 | L4: Ealing | M4: E09000009 | N4: Ealing | O4: Ealing Central and Acton | P4: London | Q4: 0 | R4: 0 | S4: 0 | T4: 0 | U4: 0 | V4: 0 | W4: 0 | X4: 0 | Y4: None | Z4: AP | AA4: Not OfS | AB4: NA | AC4: NA | AD4: No tariff | AE4: No WP Tariff | AF4: No TRAC | AG4: No TEF | AH4: None | AI4: Jun 2022 (other)
A5: 10000055 | B5: 1183 | C5: Abingdon and Witney College | D5: Abingdon College | E5: A14 | F5: England | G5: South East | H5: OX14 1GG | I5: -1.28696 | J5: 51.680624 | K5: E07000180 | L5: Vale of White Horse | M5: E07000180 | N5: Vale of White Horse | O5: Oxford West and Abingdon | Q5: 1 | R5: 0 | S5: 0 | T5: 0 | U5: 0 | V5: 0 | W5: 0 | X5: 1 | Y5: FEC | Z5: FEC | AA5: Approved (fee cap) | AB5: Yes | AC5: Yes | AD5: Further education and sixth form colleges | AE5: No WP Tariff | AF5: No TRAC | AG5: Silver | AH5: AoC | AI5: 0
A6: 10000248 | B6: 269 | C6: Academy of Live and Recorded Arts | D6: ALRA | E6: Not UCAS | F6: England | G6: London | H6: SW18 3SX | I6: -0.174557 | J6: 51.4533 | K6: E09000032 | L6: Wandsworth | M6: E09000032 | N6: Wandsworth | O6: Tooting | P6: London | Q6: 0 | R6: 0 | S6: 0 | T6: 1 | U6: 0 | V6: 0 | W6: 1 | X6: 0 | Y6: None | Z6: AP | AA6: Not OfS | AB6: NA | AC6: NA | AD6: No tariff | AE6: Medium | AF6: No TRAC | AG6: Silver | AH6: GuildHE | AI6: 0
A7: 10000080 | B7: 268 | C7: Access to Music Limited | D7: Access to Music | E7: Not UCAS | F7: England | G7: West Midlands | H7: B9 4AR | I7: -1.88286 | J7: 52.476431 | K7: E08000025 | L7: Birmingham | M7: E08000025 | N7: Birmingham | O7: Birmingham, Ladywood | P7: Birmingham | Q7: 0 | R7: 0 | S7: 0 | T7: 0 | U7: 0 | V7: 0 | W7: 0 | X7: 0 | Y7: None | Z7: AP | AA7: Not OfS | AB7: NA | AC7: NA | AD7: No tariff | AE7: No WP Tariff | AF7: No TRAC | AG7: No TEF | AH7: None | AI7: Jun 2022 (other)
A8: 10000093 | B8: 1182 | C8: Accrington and Rossendale College | D8: Accrington College | E8: Not UCAS | F8: England | G8: North West | H8: BB5 2AW | I8: -2.35286 | J8: 53.748697 | K8: E07000120 | L8: Hyndburn | M8: E07000120 | N8: Hyndburn | O8: Hyndburn | Q8: 0 | R8: 0 | S8: 0 | T8: 0 | U8: 0 | V8: 0 | W8: 0 | X8: 0 | Y8: None | Z8: Unknown | AA8: Not OfS | AB8: NA | AC8: NA | AD8: No tariff | AE8: No WP Tariff | AF8: No TRAC | AG8: No TEF | AH8: AoC | AI8: 0
A9: 10067853 | B9: 357 | C9: ACM Guildford Ltd | D9: ACM Guildford | E9: Not UCAS | F9: England | G9: South East | H9: GU1 4SB | I9: -0.578092 | J9: 51.236455 | K9: E07000209 | L9: Guildford | M9: E07000209 | N9: Guildford | O9: Guildford | P9: Guildford | Q9: 1 | R9: 0 | S9: 1 | T9: 1 | U9: 0 | V9: 0 | W9: 1 | X9: 0 | Y9: No university title | Z9: AP | AA9: Approved (fee cap) | AB9: Yes | AC9: Yes | AD9: Other providers | AE9: Low | AF9: No TRAC | AG9: Bronze | AH9: GuildHE | AI9: 0
A10: 10004927 | B10: 1181 | C10: Activate Learning | D10: Activate Learning | E10: O25 | F10: England | G10: South East | H10: OX1 1SA | I10: -1.264524 | J10: 51.749548 | K10: E07000178 | L10: Oxford | M10: E07000178 | N10: Oxford | O10: Oxford East | P10: Oxford | Q10: 1 | R10: 0 | S10: 0 | T10: 0 | U10: 0 | V10: 0 | W10: 1 | X10: 1 | Y10: FEC | Z10: FEC | AA10: Approved (fee cap) | AB10: Yes | AC10: Yes | AD10: Further education and sixth form colleges | AE10: No WP Tariff | AF10: No TRAC | AG10: Silver | AH10: AoC | AI10: 0
A11: 10000163 | B11: 213 | C11: AECC University College | D11: AECC | E11: A65 | F11: England | G11: South West | H11: BH5 2DF | I11: -1.828772 | J11: 50.727261 | K11: E06000058 | L11: Bournemouth, Christchurch and Poole | M11: E06000058 | N11: Bournemouth, Christchurch and Poole | O11: Bournemouth East | P11: Bournemouth | Q11: 1 | R11: 0 | S11: 1 | T11: 1 | U11: 0 | V11: 0 | W11: 1 | X11: 1 | Y11: University Title | Z11: HEI | AA11: Approved (fee cap) | AB11: Yes | AC11: Yes | AD11: Other providers | AE11: Medium | AF11: E | AG11: Silver | AH11: GuildHE | AI11: 0
A12: 10000216 | B12: 285 | C12: All Nations Christian College Limited | D12: All Nations | E12: Not UCAS | F12: England | G12: East of England | H12: SG12 8LX | I12: 0.000933 | J12: 51.80252 | K12: E07000242 | L12: East Hertfordshire | M12: E07000242 | N12: East Hertfordshire | O12: Hertford and Stortford | Q12: 1 | R12: 0 | S12: 0 | T12: 1 | U12: 0 | V12: 0 | W12: 0 | X12: 0 | Y12: No university title | Z12: AP | AA12: Approved | AB12: No | AC12: No | AD12: No tariff | AE12: c | AF12: No TRAC | AG12: No TEF | AH12: None | AI12: 0
A13: 10032036 | B13: 353 | C13: Amity Global Education Ltd | D13: Amity | E13: A11 | F13: England | G13: London | H13: WC1B 3HN | I13: -0.131146 | J13: 51.519206 | K13: E09000007 | L13: Camden | M13: E09000007 | N13: Camden | O13: Holborn and St Pancras | P13: London | Q13: 1 | R13: 0 | S13: 1 | T13: 1 | U13: 0 | V13: 0 | W13: 1 | X13: 1 | Y13: University Title | Z13: AP | AA13: Approved (fee cap) | AB13: Yes | AC13: No | AD13: Other providers | AE13: No WP Tariff | AF13: No TRAC | AG13: Provisional | AH13: None | AI13: 0
A14: UCAS: no UKPRN | B14: No INSTID | C14: Amsterdam Fashion Academy | D14: Amsterdam Fashion | E14: A57 | F14: NA | G14: NA | H14: NA | I14: 4.901927 | J14: 52.359848 | K14: International | L14: International | M14: International | N14: International | O14: International | P14: NA | Q14: 0 | R14: 0 | S14: 0 | T14: 0 | U14: 0 | V14: 0 | W14: 0 | X14: 1 | Y14: None | Z14: Unknown | AA14: Not OfS | AB14: NA | AC14: NA | AD14: No tariff | AE14: No WP Tariff | AF14: No TRAC | AG14: No TEF | AH14: None | AI14: 0
A15: 10000291 | B15: 47 | C15: Anglia Ruskin University Higher Education Corporation | D15: Anglia Ruskin | E15: A60 | F15: England | G15: East of England | H15: CM1 1SQ | I15: 0.474495 | J15: 51.741381 | K15: E07000070 | L15: Chelmsford | M15: E07000070 | N15: Chelmsford | O15: Chelmsford | P15: Chelmsford | Q15: 1 | R15: 0 | S15: 1 | T15: 1 | U15: 0 | V15: 0 | W15: 1 | X15: 1 | Y15: University Title | Z15: HEI | AA15: Approved (fee cap) | AB15: Yes | AC15: Yes | AD15: HEIs with low scores | AE15: Low | AF15: D | AG15: Silver | AH15: University Alliance | AI15: 0
A16: 10062759 | B16: 432 | C16: Applied Business Academy Limited | D16: Applied Business Academy | E16: Not UCAS | F16: England | G16: London | H16: E14 9RH | I16: -0.014275 | J16: 51.49744 | K16: E09000030 | L16: Tower Hamlets | M16: E09000030 | N16: Tower Hamlets | O16: Poplar and Limehouse | P16: London | Q16: 1 | R16: 0 | S16: 0 | T16: 1 | U16: 0 | V16: 0 | W16: 1 | X16: 0 | Y16: No university title | Z16: Unknown | AA16: Approved | AB16: No | AC16: No | AD16: No tariff | AE16: No WP Tariff | AF16: No TRAC | AG16: No TEF | AH16: None | AI16: Jan 2021 (OfS register)
A17: 10008071 | B17: 323 | C17: Architectural Association (Incorporated) | D17: Architectural Association | E17: Not UCAS | F17: England | G17: London | H17: WC1B 3ES | I17: -0.130697 | J17: 51.518218 | K17: E09000007 | L17: Camden | M17: E09000007 | N17: Camden | O17: Holborn and St Pancras | P17: London | Q17: 1 | R17: 0 | S17: 0 | T17: 1 | U17: 0 | V17: 0 | W17: 0 | X17: 0 | Y17: No university title | Z17: AP | AA17: Approved | AB17: No | AC17: No | AD17: No tariff | AE17: c | AF17: No TRAC | AG17: No TEF | AH17: None | AI17: 0
A18: 10005451 | B18: 333 | C18: Arden University Limited | D18: Arden Uni | E18: R25 | F18: England | G18: West Midlands | H18: CV3 4FJ | I18: -1.466384 | J18: 52.373008 | K18: E07000222 | L18: Warwick | M18: E07000222 | N18: Warwick | O18: Kenilworth and Southam | Q18: 1 | R18: 0 | S18: 1 | T18: 1 | U18: 0 | V18: 0 | W18: 1 | X18: 1 | Y18: University Title | Z18: AP | AA18: Approved (fee cap) | AB18: Yes | AC18: Yes | AD18: Other providers | AE18: Low | AF18: No TRAC | AG18: Provisional | AH18: None | AI18: 0
A19: 10044534 | B19: No INSTID | C19: Ark Teacher Training | D19: Ark Teacher Training | E19: Not UCAS | F19: England | G19: London | H19: WC2B 6TD | I19: -0.119475 | J19: 51.515334 | K19: E09000007 | L19: Camden | M19: E09000007 | N19: Camden | O19: Holborn and St Pancras | P19: London | Q19: 0 | R19: 0 | S19: 0 | T19: 0 | U19: 0 | V19: 0 | W19: 1 | X19: 0 | Y19: None | Z19: SCITT | AA19: Not OfS | AB19: NA | AC19: NA | AD19: No tariff | AE19: No WP Tariff | AF19: No TRAC | AG19: No TEF | AH19: None | AI19: Apr 2021 (SLC)
A20: 10034759 | B20: No INSTID | C20: Arthur Terry National Teaching School Alliance | D20: Arthur Terry | E20: Not UCAS | F20: England | G20: West Midlands | H20: B74 4RZ | I20: -1.836208 | J20: 52.589596 | K20: E08000025 | L20: Birmingham | M20: E08000025 | N20: Birmingham | O20: Sutton Coldfield | P20: Sutton Coldfield | Q20: 0 | R20: 0 | S20: 0 | T20: 0 | U20: 0 | V20: 0 | W20: 1 | X20: 0 | Y20: None | Z20: Unknown | AA20: Not OfS | AB20: NA | AC20: NA | AD20: No tariff | AE20: No WP Tariff | AF20: No TRAC | AG20: No TEF | AH20: None | AI20: Apr 2021 (SLC)
A21: 10000381 | B21: 244 | C21: Arts Educational Schools(The) | D21: Arts Educational Schools | E21: Not UCAS | F21: England | G21: London | H21: W4 1LY | I21: -0.252435 | J21: 51.49596 | K21: E09000018 | L21: Hounslow | M21: E09000018 | N21: Hounslow | O21: Brentford and Isleworth | P21: London | Q21: 1 | R21: 0 | S21: 0 | T21: 1 | U21: 0 | V21: 0 | W21: 1 | X21: 0 | Y21: No university title | Z21: AP | AA21: Approved | AB21: No | AC21: No | AD21: No tariff | AE21: Medium | AF21: No TRAC | AG21: Gold | AH21: None | AI21: 0
A22: 10000385 | B22: 197 | C22: Arts University Bournemouth | D22: Arts Bournemouth | E22: A66 | F22: England | G22: South West | H22: BH12 5HH | I22: -1.897728 | J22: 50.741808 | K22: E06000058 | L22: Bournemouth, Christchurch and Poole | M22: E06000058 | N22: Bournemouth, Christchurch and Poole | O22: Bournemouth West | P22: Poole | Q22: 1 | R22: 0 | S22: 1 | T22: 1 | U22: 0 | V22: 0 | W22: 1 | X22: 1 | Y22: University Title | Z22: HEI | AA22: Approved (fee cap) | AB22: Yes | AC22: Yes | AD22: Specialist HEI | AE22: Medium | AF22: F | AG22: Gold | AH22: GuildHE | AI22: 0
A23: 10005127 | B23: 230 | C23: Arts University Plymouth | D23: Plymouth Art | E23: P65 | F23: England | G23: South West | H23: PL4 8AT | I23: -4.137411 | J23: 50.37341 | K23: E06000026 | L23: Plymouth | M23: E06000026 | N23: Plymouth | O23: Plymouth, Sutton and Devonport | P23: Plymouth | Q23: 1 | R23: 0 | S23: 1 | T23: 1 | U23: 0 | V23: 0 | W23: 1 | X23: 1 | Y23: University Title | Z23: HEI | AA23: Approved (fee cap) | AB23: Yes | AC23: Yes | AD23: Specialist HEI | AE23: Medium | AF23: F | AG23: Bronze | AH23: GuildHE | AI23: 0
A24: 10004011 | B24: No INSTID | C24: ARU London | D24: ARU London | E24: L63 | F24: England | G24: London | H24: EC1N 6RA | I24: -0.106332 | J24: 51.518423 | K24: E09000007 | L24: Camden | M24: E09000007 | N24: Camden | O24: Holborn and St Pancras | P24: London | Q24: 0 | R24: 0 | S24: 0 | T24: 0 | U24: 0 | V24: 0 | W24: 0 | X24: 1 | Y24: None | Z24: Unknown | AA24: Not OfS | AB24: NA | AC24: NA | AD24: No tariff | AE24: No WP Tariff | AF24: No TRAC | AG24: No TEF | AH24: None | AI24: 0
A25: 10000415 | B25: 1179 | C25: Askham Bryan College | D25: Askham Bryan College | E25: A70 | F25: England | G25: Yorkshire and The Humber | H25: YO23 3FR | I25: -1.161491 | J25: 53.920657 | K25: E06000014 | L25: York | M25: E06000014 | N25: York | O25: York Outer | Q25: 1 | R25: 0 | S25: 0 | T25: 0 | U25: 0 | V25: 0 | W25: 1 | X25: 1 | Y25: FEC | Z25: FEC | AA25: Approved (fee cap) | AB25: Yes | AC25: Yes | AD25: Further education and sixth form colleges | AE25: No WP Tariff | AF25: No TRAC | AG25: Bronze | AH25: AoC | AI25: 0
A26: 10020416 | B26: 225 | C26: Assemblies of God Incorporated | D26: Assemblies of God | E26: Not UCAS | F26: England | G26: North West | H26: M3 7BE | I26: -2.253974 | J26: 53.484297 | K26: E08000006 | L26: Salford | M26: E08000006 | N26: Salford | O26: Salford and Eccles | P26: Salford | Q26: 1 | R26: 0 | S26: 0 | T26: 1 | U26: 0 | V26: 0 | W26: 0 | X26: 0 | Y26: No university title | Z26: AP | AA26: Approved | AB26: No | AC26: No | AD26: No tariff | AE26: c | AF26: No TRAC | AG26: Bronze | AH26: None | AI26: 0
A27: 10055360 | B27: No INSTID | C27: Associated Merseyside Partnership Scitt | D27: Associated Merseyside Scitt | E27: Not UCAS | F27: England | G27: North West | H27: L31 1EP | I27: -2.92347 | J27: 53.495613 | K27: E08000014 | L27: Sefton | M27: E08000014 | N27: Sefton | O27: Sefton Central | Q27: 0 | R27: 0 | S27: 0 | T27: 0 | U27: 0 | V27: 0 | W27: 1 | X27: 0 | Y27: None | Z27: SCITT | AA27: Not OfS | AB27: NA | AC27: NA | AD27: No tariff | AE27: No WP Tariff | AF27: No TRAC | AG27: No TEF | AH27: None | AI27: Apr 2021 (SLC)
A28: 10007759 | B28: 108 | C28: Aston University | D28: Aston | E28: A80 | F28: England | G28: West Midlands | H28: B4 7ET | I28: -1.890952 | J28: 52.486637 | K28: E08000025 | L28: Birmingham | M28: E08000025 | N28: Birmingham | O28: Birmingham, Ladywood | P28: Birmingham | Q28: 1 | R28: 0 | S28: 1 | T28: 1 | U28: 0 | V28: 0 | W28: 1 | X28: 1 | Y28: University Title | Z28: HEI | AA28: Approved (fee cap) | AB28: Yes | AC28: Yes | AD28: HEIs with high scores | AE28: Medium | AF28: B | AG28: Gold | AH28: None | AI28: 0
A29: 10000473 | B29: 1178 | C29: Aylesbury College | D29: Aylesbury College | E29: Not UCAS | F29: England | G29: South East | H29: HP21 8PD | I29: -0.822655 | J29: 51.813857 | K29: E06000060 | L29: Buckinghamshire | M29: E06000060 | N29: Buckinghamshire | O29: Aylesbury | Q29: 1 | R29: 0 | S29: 0 | T29: 0 | U29: 0 | V29: 0 | W29: 0 | X29: 0 | Y29: FEC | Z29: FEC | AA29: Approved (fee cap) | AB29: Yes | AC29: No | AD29: Further education and sixth form colleges | AE29: No WP Tariff | AF29: No TRAC | AG29: No TEF | AH29: None | AI29: 0
A30: 10036456 | B30: 426 | C30: Backstage Academy (Training) Ltd | D30: Backstage Academy | E30: Not UCAS | F30: England | G30: Yorkshire and The Humber | H30: WF9 3AP | I30: -1.309879 | J30: 53.589945 | K30: E08000036 | L30: Wakefield | M30: E08000036 | N30: Wakefield | O30: Hemsworth | Q30: 1 | R30: 0 | S30: 1 | T30: 1 | U30: 0 | V30: 0 | W30: 0 | X30: 0 | Y30: No university title | Z30: Unknown | AA30: Approved (fee cap) | AB30: Yes | AC30: Yes | AD30: Other providers | AE30: No WP Tariff | AF30: No TRAC | AG30: No TEF | AH30: None | AI30: 0
A31: 10042364 | B31: 324 | C31: Ballet West | D31: Ballet West | E31: Not UCAS | F31: Scotland | G31: Scotland | H31: PA35 1HP | I31: -5.226522 | J31: 56.426118 | K31: S12000035 | L31: Argyll and Bute | M31: S30000036 | N31: Argyll and Bute Mainland | O31: Argyll and Bute | P31: NA | Q31: 0 | R31: 0 | S31: 0 | T31: 0 | U31: 0 | V31: 0 | W31: 0 | X31: 0 | Y31: None | Z31: AP | AA31: Not OfS | AB31: NA | AC31: NA | AD31: No tariff | AE31: c | AF31: No TRAC | AG31: No TEF | AH31: None | AI31: 0
A32: 10007857 | B32: 178 | C32: Bangor University | D32: Bangor | E32: B06 | F32: Wales | G32: Wales | H32: LL57 2DG | I32: -4.129437 | J32: 53.229193 | K32: W06000002 | L32: Gwynedd | M32: W06000002 | N32: Gwynedd | O32: Arfon | Q32: 0 | R32: 1 | S32: 1 | T32: 1 | U32: 0 | V32: 0 | W32: 1 | X32: 1 | Y32: None | Z32: HEI | AA32: Not OfS | AB32: NA | AC32: NA | AD32: No tariff | AE32: Medium | AF32: B | AG32: Gold | AH32: None | AI32: 0
A33: 10000528 | B33: 1177 | C33: Barking and Dagenham College | D33: Barking College | E33: B11 | F33: England | G33: London | H33: RM7 0XU | I33: 0.174564 | J33: 51.56033 | K33: E09000002 | L33: Barking and Dagenham | M33: E09000002 | N33: Barking and Dagenham | O33: Dagenham and Rainham | P33: London | Q33: 0 | R33: 0 | S33: 0 | T33: 0 | U33: 0 | V33: 0 | W33: 0 | X33: 1 | Y33: FEC | Z33: FEC | AA33: Not OfS | AB33: NA | AC33: NA | AD33: No tariff | AE33: No WP Tariff | AF33: No TRAC | AG33: No TEF | AH33: AoC | AI33: 0
A34: 10000533 | B34: 1174 | C34: Barnet & Southgate College | D34: Barnet College | E34: B08 | F34: England | G34: London | H34: EN5 4AZ | I34: -0.2003 | J34: 51.652379 | K34: E09000003 | L34: Barnet | M34: E09000003 | N34: Barnet | O34: Chipping Barnet | P34: London | Q34: 1 | R34: 0 | S34: 0 | T34: 0 | U34: 0 | V34: 0 | W34: 1 | X34: 1 | Y34: FEC | Z34: FEC | AA34: Approved (fee cap) | AB34: Yes | AC34: Yes | AD34: Further education and sixth form colleges | AE34: No WP Tariff | AF34: No TRAC | AG34: Bronze | AH34: AoC | AI34: 0
A35: 10000534 | B35: 1176 | C35: Barnfield College | D35: Barnfield College | E35: B09 | F35: England | G35: East of England | H35: LU2 7BF | I35: -0.421883 | J35: 51.90603 | K35: E06000032 | L35: Luton | M35: E06000032 | N35: Luton | O35: Luton North | P35: Luton | Q35: 0 | R35: 0 | S35: 0 | T35: 0 | U35: 0 | V35: 0 | W35: 0 | X35: 1 | Y35: None | Z35: Unknown | AA35: Not OfS | AB35: NA | AC35: NA | AD35: No tariff | AE35: No WP Tariff | AF35: No TRAC | AG35: No TEF | AH35: AoC | AI35: 0
A36: 10000536 | B36: 1175 | C36: Barnsley College | D36: Barnsley College | E36: B13 | F36: England | G36: Yorkshire and The Humber | H36: S70 2AX | I36: -1.482572 | J36: 53.556624 | K36: E08000016 | L36: Barnsley | M36: E08000016 | N36: Barnsley | O36: Barnsley Central | P36: Barnsley | Q36: 1 | R36: 0 | S36: 0 | T36: 0 | U36: 0 | V36: 0 | W36: 1 | X36: 1 | Y36: FEC | Z36: FEC | AA36: Approved (fee cap) | AB36: Yes | AC36: Yes | AD36: Further education and sixth form colleges | AE36: No WP Tariff | AF36: No TRAC | AG36: Provisional | AH36: AoC | AI36: 0
A37: 10000560 | B37: 1173 | C37: Basingstoke College of Technology | D37: Basingstoke College | E37: Not UCAS | F37: England | G37: South East | H37: RG21 8TN | I37: -1.095958 | J37: 51.26336 | K37: E07000084 | L37: Basingstoke and Deane | M37: E07000084 | N37: Basingstoke and Deane | O37: Basingstoke | P37: Basingstoke | Q37: 1 | R37: 0 | S37: 0 | T37: 0 | U37: 0 | V37: 0 | W37: 0 | X37: 0 | Y37: FEC | Z37: FEC | AA37: Approved (fee cap) | AB37: Yes | AC37: Yes | AD37: Further education and sixth form colleges | AE37: No WP Tariff | AF37: No TRAC | AG37: No TEF | AH37: AoC | AI37: 0
A38: 10001465 | B38: 1172 | C38: Bath College | D38: Bath College | E38: B21 | F38: England | G38: South West | H38: BA1 1UP | I38: -2.362652 | J38: 51.379717 | K38: E06000022 | L38: Bath and North East Somerset | M38: E06000022 | N38: Bath and North East Somerset | O38: Bath | P38: Bath | Q38: 1 | R38: 0 | S38: 0 | T38: 0 | U38: 0 | V38: 0 | W38: 1 | X38: 1 | Y38: FEC | Z38: FEC | AA38: Approved (fee cap) | AB38: Yes | AC38: Yes | AD38: Further education and sixth form colleges | AE38: No WP Tariff | AF38: No TRAC | AG38: Silver | AH38: AoC | AI38: 0
A39: 10000571 | B39: 48 | C39: Bath Spa University | D39: Bath Spa | E39: B20 | F39: England | G39: South West | H39: BA2 9BN | I39: -2.440912 | J39: 51.373209 | K39: E06000022 | L39: Bath and North East Somerset | M39: E06000022 | N39: Bath and North East Somerset | O39: North East Somerset | Q39: 1 | R39: 0 | S39: 1 | T39: 1 | U39: 0 | V39: 0 | W39: 1 | X39: 1 | Y39: University Title | Z39: HEI | AA39: Approved (fee cap) | AB39: Yes | AC39: Yes | AD39: HEIs with medium scores | AE39: Low | AF39: E | AG39: Silver | AH39: MillionPlus, GuildHE | AI39: 0
A40: 10000911 | B40: 400 | C40: BCNO Limited | D40: BCNO | E40: B81 | F40: England | G40: London | H40: NW3 5RR | I40: -0.179372 | J40: 51.547841 | K40: E09000007 | L40: Camden | M40: E09000007 | N40: Camden | O40: Hampstead and Kilburn | P40: London | Q40: 1 | R40: 0 | S40: 0 | T40: 1 | U40: 0 | V40: 0 | W40: 0 | X40: 1 | Y40: No university title | Z40: Unknown | AA40: Approved | AB40: No | AC40: No | AD40: No tariff | AE40: No WP Tariff | AF40: No TRAC | AG40: No TEF | AH40: None | AI40: 0
A41: 10058882 | B41: No INSTID | C41: Bec Teacher Training | D41: Bec Teacher Training | E41: Not UCAS | F41: England | G41: East of England | H41: SS12 0LZ | I41: 0.510282 | J41: 51.605517 | K41: E07000066 | L41: Basildon | M41: E07000066 | N41: Basildon | O41: Rayleigh and Wickford | Q41: 0 | R41: 0 | S41: 0 | T41: 0 | U41: 0 | V41: 0 | W41: 1 | X41: 0 | Y41: None | Z41: SCITT | AA41: Not OfS | AB41: NA | AC41: NA | AD41: No tariff | AE41: No WP Tariff | AF41: No TRAC | AG41: No TEF | AH41: None | AI41: Feb 2022 (SLC)
A42: 10000610 | B42: 1171 | C42: Bedford College | D42: Bedford College | E42: B23 | F42: England | G42: East of England | H42: MK42 9AH | I42: -0.468552 | J42: 52.133347 | K42: E06000055 | L42: Bedford | M42: E06000055 | N42: Bedford | O42: Bedford | P42: Bedford | Q42: 1 | R42: 0 | S42: 0 | T42: 0 | U42: 0 | V42: 0 | W42: 1 | X42: 1 | Y42: FEC | Z42: FEC | AA42: Approved (fee cap) | AB42: Yes | AC42: Yes | AD42: Further education and sixth form colleges | AE42: No WP Tariff | AF42: No TRAC | AG42: No TEF | AH42: AoC | AI42: 0
A43: 10020680 | B43: 345 | C43: Belfast Metropolitan College | D43: Belfast Met | E43: Not UCAS | F43: Northern Ireland | G43: Northern Ireland | H43: BT3 9FQ | I43: -5.911865 | J43: 54.604763 | K43: N09000003 | L43: Belfast | M43: N09000003 | N43: Belfast | O43: Belfast East | P43: NA | Q43: 0 | R43: 0 | S43: 0 | T43: 0 | U43: 0 | V43: 0 | W43: 0 | X43: 0 | Y43: None | Z43: Unknown | AA43: Not OfS | AB43: NA | AC43: NA | AD43: No tariff | AE43: No WP Tariff | AF43: No TRAC | AG43: No TEF | AH43: None | AI43: Feb 2021 (Graduate outcomes)
A44: 10008098 | B44: 403 | C44: Bellerbys Educational Services | D44: Bellerbys | E44: Not UCAS | F44: England | G44: South East | H44: BN1 4LF | I44: -0.140833 | J44: 50.832036 | K44: E06000043 | L44: Brighton and Hove | M44: E06000043 | N44: Brighton and Hove | O44: Brighton, Pavilion | P44: Brighton and Hove | Q44: 1 | R44: 0 | S44: 0 | T44: 1 | U44: 0 | V44: 0 | W44: 0 | X44: 0 | Y44: Not applicable | Z44: Unknown | AA44: Approved | AB44: No | AC44: No | AD44: No tariff | AE44: No WP Tariff | AF44: No TRAC | AG44: No TEF | AH44: None | AI44: 0
A45: 10000670 | B45: 1188 | C45: Bexhill College | D45: Bexhill College | E45: Not UCAS | F45: England | G45: South East | H45: TN40 2JG | I45: 0.490934 | J45: 50.847112 | K45: E07000064 | L45: Rother | M45: E07000064 | N45: Rother | O45: Bexhill and Battle | Q45: 1 | R45: 0 | S45: 0 | T45: 0 | U45: 0 | V45: 0 | W45: 0 | X45: 0 | Y45: FEC | Z45: FEC | AA45: Approved (fee cap) | AB45: Yes | AC45: Yes | AD45: Further education and sixth form colleges | AE45: No WP Tariff | AF45: No TRAC | AG45: No TEF | AH45: AoC | AI45: 0
A46: 10037544 | B46: 232 | C46: BIMM Limited | D46: BIMM | E46: B39 | F46: England | G46: South East | H46: BN1 1HG | I46: -0.139682 | J46: 50.820995 | K46: E06000043 | L46: Brighton and Hove | M46: E06000043 | N46: Brighton and Hove | O46: Brighton, Pavilion | P46: Brighton and Hove | Q46: 1 | R46: 0 | S46: 1 | T46: 1 | U46: 0 | V46: 0 | W46: 1 | X46: 1 | Y46: No university title | Z46: AP | AA46: Approved (fee cap) | AB46: Yes | AC46: Yes | AD46: Other providers | AE46: Low | AF46: No TRAC | AG46: Bronze | AH46: GuildHE | AI46: 0
A47: 10007760 | B47: 127 | C47: Birkbeck College | D47: Birkbeck | E47: B24 | F47: England | G47: London | H47: WC1E 7HX | I47: -0.130359 | J47: 51.521891 | K47: E09000007 | L47: Camden | M47: E09000007 | N47: Camden | O47: Holborn and St Pancras | P47: London | Q47: 1 | R47: 0 | S47: 1 | T47: 1 | U47: 0 | V47: 0 | W47: 1 | X47: 1 | Y47: Not applicable | Z47: HEI | AA47: Approved (fee cap) | AB47: Yes | AC47: Yes | AD47: Specialist HEI | AE47: Low | AF47: B | AG47: Silver | AH47: London Higher | AI47: 0
A48: 10007140 | B48: 52 | C48: Birmingham City University | D48: Birmingham City | E48: B25 | F48: England | G48: West Midlands | H48: B5 5JU | I48: -1.888824 | J48: 52.481921 | K48: E08000025 | L48: Birmingham | M48: E08000025 | N48: Birmingham | O48: Birmingham, Ladywood | P48: Birmingham | Q48: 1 | R48: 0 | S48: 1 | T48: 1 | U48: 0 | V48: 0 | W48: 1 | X48: 1 | Y48: University Title | Z48: HEI | AA48: Approved (fee cap) | AB48: Yes | AC48: Yes | AD48: HEIs with low scores | AE48: Medium | AF48: D | AG48: Silver | AH48: University Alliance | AI48: 0
A49: 10006442 | B49: 1169 | C49: Birmingham Metropolitan College | D49: Birmingham Met | E49: B30 | F49: England | G49: West Midlands | H49: B4 7PS | I49: -1.889341 | J49: 52.48321 | K49: E08000025 | L49: Birmingham | M49: E08000025 | N49: Birmingham | O49: Birmingham, Ladywood | P49: Birmingham | Q49: 1 | R49: 0 | S49: 0 | T49: 0 | U49: 0 | V49: 0 | W49: 1 | X49: 1 | Y49: FEC | Z49: FEC | AA49: Approved (fee cap) | AB49: Yes | AC49: Yes | AD49: Further education and sixth form colleges | AE49: No WP Tariff | AF49: No TRAC | AG49: Provisional | AH49: AoC | AI49: 0
A50: 10000720 | B50: 1168 | C50: Bishop Auckland College | D50: Bishop College | E50: Not UCAS | F50: England | G50: North East | H50: DL14 6JZ | I50: -1.69652 | J50: 54.65052 | K50: E06000047 | L50: County Durham | M50: E06000047 | N50: County Durham | O50: Bishop Auckland | Q50: 1 | R50: 0 | S50: 0 | T50: 0 | U50: 0 | V50: 0 | W50: 1 | X50: 0 | Y50: FEC | Z50: FEC | AA50: Approved (fee cap) | AB50: Yes | AC50: Yes | AD50: Further education and sixth form colleges | AE50: No WP Tariff | AF50: No TRAC | AG50: Bronze | AH50: AoC | AI50: 0
A51: 10000721 | B51: 1167 | C51: Bishop Burton College | D51: Bishop Burton College | E51: B37 | F51: England | G51: Yorkshire and The Humber | H51: HU17 8QG | I51: -0.503445 | J51: 53.848058 | K51: E06000011 | L51: East Riding of Yorkshire | M51: E06000011 | N51: East Riding of Yorkshire | O51: Beverley and Holderness | Q51: 1 | R51: 0 | S51: 0 | T51: 0 | U51: 0 | V51: 0 | W51: 1 | X51: 1 | Y51: FEC | Z51: FEC | AA51: Approved (fee cap) | AB51: Yes | AC51: Yes | AD51: Further education and sixth form colleges | AE51: No WP Tariff | AF51: No TRAC | AG51: Bronze | AH51: AoC | AI51: 0
A52: 10007811 | B52: 7 | C52: Bishop Grosseteste University | D52: Bishop Grosseteste | E52: B38 | F52: England | G52: East Midlands | H52: LN1 3DY | I52: -0.537139 | J52: 53.243563 | K52: E07000138 | L52: Lincoln | M52: E07000138 | N52: Lincoln | O52: Lincoln | P52: Lincoln | Q52: 1 | R52: 0 | S52: 1 | T52: 1 | U52: 0 | V52: 0 | W52: 1 | X52: 1 | Y52: University Title | Z52: HEI | AA52: Approved (fee cap) | AB52: Yes | AC52: Yes | AD52: Specialist HEI | AE52: Low | AF52: E | AG52: Gold | AH52: GuildHE, Cathedrals Group | AI52: 0
A53: 10000747 | B53: 1166 | C53: Blackburn College | D53: Blackburn College | E53: B40 | F53: England | G53: North West | H53: BB2 1LH | I53: -2.489745 | J53: 53.748575 | K53: E06000008 | L53: Blackburn with Darwen | M53: E06000008 | N53: Blackburn with Darwen | O53: Blackburn | P53: Blackburn | Q53: 1 | R53: 0 | S53: 0 | T53: 0 | U53: 0 | V53: 0 | W53: 1 | X53: 1 | Y53: FEC | Z53: FEC | AA53: Approved (fee cap) | AB53: Yes | AC53: Yes | AD53: Further education and sixth form colleges | AE53: No WP Tariff | AF53: No TRAC | AG53: Bronze | AH53: AoC | AI53: 0
A54: 10000754 | B54: 1165 | C54: Blackpool and the Fylde College | D54: Blackpool College | E54: B41 | F54: England | G54: North West | H54: FY2 0HB | I54: -3.027626 | J54: 53.859345 | K54: E06000009 | L54: Blackpool | M54: E06000009 | N54: Blackpool | O54: Blackpool North and Cleveleys | P54: Blackpool | Q54: 1 | R54: 0 | S54: 0 | T54: 0 | U54: 0 | V54: 0 | W54: 1 | X54: 1 | Y54: FEC | Z54: FEC | AA54: Approved (fee cap) | AB54: Yes | AC54: Yes | AD54: Further education and sixth form colleges | AE54: No WP Tariff | AF54: No TRAC | AG54: Gold | AH54: AoC | AI54: 0
A55: 10004061 | B55: 238 | C55: Bloomsbury Institute Limited | D55: Bloomsbury | E55: L73 | F55: England | G55: London | H55: WC1B 3RA | I55: -0.129063 | J55: 51.51948 | K55: E09000007 | L55: Camden | M55: E09000007 | N55: Camden | O55: Holborn and St Pancras | P55: London | Q55: 1 | R55: 0 | S55: 1 | T55: 1 | U55: 0 | V55: 0 | W55: 1 | X55: 1 | Y55: No university title | Z55: AP | AA55: Approved (fee cap) | AB55: Yes | AC55: No | AD55: Other providers | AE55: Low | AF55: No TRAC | AG55: Provisional | AH55: None | AI55: 0
A56: 10000794 | B56: 1164 | C56: Bolton College | D56: Bolton College | E56: Not UCAS | F56: England | G56: North West | H56: BL3 5BG | I56: -2.437096 | J56: 53.574721 | K56: E08000001 | L56: Bolton | M56: E08000001 | N56: Bolton | O56: Bolton South East | P56: Bolton | Q56: 1 | R56: 0 | S56: 0 | T56: 0 | U56: 0 | V56: 0 | W56: 0 | X56: 0 | Y56: FEC | Z56: FEC | AA56: Approved (fee cap) | AB56: No | AC56: No | AD56: Further education and sixth form colleges | AE56: No WP Tariff | AF56: No TRAC | AG56: No TEF | AH56: AoC | AI56: 0
A57: 10000812 | B57: 1163 | C57: Boston College | D57: Boston College | E57: Not UCAS | F57: England | G57: East Midlands | H57: PE21 6JF | I57: -0.014959 | J57: 52.973254 | K57: E07000136 | L57: Boston | M57: E07000136 | N57: Boston | O57: Boston and Skegness | Q57: 1 | R57: 0 | S57: 0 | T57: 0 | U57: 0 | V57: 0 | W57: 1 | X57: 0 | Y57: FEC | Z57: FEC | AA57: Approved (fee cap) | AB57: Yes | AC57: Yes | AD57: Further education and sixth form colleges | AE57: No WP Tariff | AF57: No TRAC | AG57: Bronze | AH57: AoC | AI57: 0
A58: 10000820 | B58: 1162 | C58: Bournemouth and Poole College, the | D58: Bournemouth College | E58: B49 | F58: England | G58: South West | H58: BH14 0LS | I58: -1.961881 | J58: 50.724709 | K58: E06000058 | L58: Bournemouth, Christchurch and Poole | M58: E06000058 | N58: Bournemouth, Christchurch and Poole | O58: Poole | P58: Poole | Q58: 1 | R58: 0 | S58: 0 | T58: 0 | U58: 0 | V58: 0 | W58: 1 | X58: 1 | Y58: FEC | Z58: FEC | AA58: Approved (fee cap) | AB58: Yes | AC58: Yes | AD58: Further education and sixth form colleges | AE58: No WP Tariff | AF58: No TRAC | AG58: Bronze | AH58: AoC | AI58: 0
A59: 10000824 | B59: 50 | C59: Bournemouth University Higher Education Corporation | D59: Bournemouth | E59: B50 | F59: England | G59: South West | H59: BH12 5BB | I59: -1.897168 | J59: 50.742979 | K59: E06000058 | L59: Bournemouth, Christchurch and Poole | M59: E06000058 | N59: Bournemouth, Christchurch and Poole | O59: Bournemouth West | P59: Poole | Q59: 1 | R59: 0 | S59: 1 | T59: 1 | U59: 0 | V59: 0 | W59: 1 | X59: 1 | Y59: University Title | Z59: HEI | AA59: Approved (fee cap) | AB59: Yes | AC59: Yes | AD59: HEIs with medium scores | AE59: Medium | AF59: E | AG59: Silver | AH59: None | AI59: 0
A60: 10031982 | B60: 214 | C60: BPP University Limited | D60: BPP | E60: B54 | F60: England | G60: London | H60: EC2M 5PD | I60: -0.085865 | J60: 51.516956 | K60: E09000001 | L60: City of London | M60: E09000001 | N60: City of London | O60: Cities of London and Westminster | P60: London | Q60: 1 | R60: 0 | S60: 0 | T60: 1 | U60: 0 | V60: 0 | W60: 1 | X60: 1 | Y60: University Title | Z60: AP | AA60: Approved | AB60: No | AC60: No | AD60: No tariff | AE60: c | AF60: No TRAC | AG60: No TEF | AH60: None | AI60: 0
A61: 10000833 | B61: 1192 | C61: Bracknell and Wokingham College | D61: Bracknell and Wokingham College | E61: Not UCAS | F61: England | G61: South East | H61: RG12 1DJ | I61: -0.744655 | J61: 51.416324 | K61: E06000036 | L61: Bracknell Forest | M61: E06000036 | N61: Bracknell Forest | O61: Bracknell | P61: Bracknell | Q61: 0 | R61: 0 | S61: 0 | T61: 0 | U61: 0 | V61: 0 | W61: 0 | X61: 0 | Y61: None | Z61: Unknown | AA61: Not OfS | AB61: NA | AC61: NA | AD61: No tariff | AE61: No WP Tariff | AF61: No TRAC | AG61: No TEF | AH61: None | AI61: Feb 2022 (other)
A62: 10000840 | B62: 1161 | C62: Bradford College | D62: Bradford College | E62: B60 | F62: England | G62: Yorkshire and The Humber | H62: BD7 1AY | I62: -1.768111 | J62: 53.791677 | K62: E08000032 | L62: Bradford | M62: E08000032 | N62: Bradford | O62: Bradford West | P62: Bradford | Q62: 1 | R62: 0 | S62: 0 | T62: 0 | U62: 0 | V62: 0 | W62: 1 | X62: 1 | Y62: FEC | Z62: FEC | AA62: Approved (fee cap) | AB62: Yes | AC62: Yes | AD62: Further education and sixth form colleges | AE62: No WP Tariff | AF62: No TRAC | AG62: Bronze | AH62: AoC | AI62: 0
A63: 10008119 | B63: No INSTID | C63: Bridgend College | D63: Bridgend College | E63: B68 | F63: Wales | G63: Wales | H63: CF31 3DF | I63: -3.571949 | J63: 51.499904 | K63: W06000013 | L63: Bridgend | M63: W06000013 | N63: Bridgend | O63: Bridgend | Q63: 0 | R63: 0 | S63: 0 | T63: 0 | U63: 0 | V63: 0 | W63: 0 | X63: 1 | Y63: None | Z63: Unknown | AA63: Not OfS | AB63: NA | AC63: NA | AD63: No tariff | AE63: No WP Tariff | AF63: No TRAC | AG63: No TEF | AH63: None | AI63: 0
A64: 10000878 | B64: 1158 | C64: Bridgwater and Taunton College | D64: Bridgwater College | E64: B70 | F64: England | G64: South West | H64: TA1 5AX | I64: -3.118879 | J64: 51.016061 | K64: E07000246 | L64: Somerset West and Taunton | M64: E07000246 | N64: Somerset West and Taunton | O64: Taunton Deane | Q64: 1 | R64: 0 | S64: 0 | T64: 0 | U64: 0 | V64: 0 | W64: 1 | X64: 1 | Y64: FEC | Z64: FEC | AA64: Approved (fee cap) | AB64: Yes | AC64: Yes | AD64: Further education and sixth form colleges | AE64: No WP Tariff | AF64: No TRAC | AG64: Silver | AH64: AoC | AI64: 0
A65: 99999999 | B65: 7006 | C65: Brighton and Sussex Medical School | D65: Brighton Medical | E65: B74 | F65: England | G65: South East | H65: BN1 9PX | I65: -0.085693 | J65: 50.864249 | K65: E06000043 | L65: Brighton and Hove | M65: E06000043 | N65: Brighton and Hove | O65: Brighton, Pavilion | Q65: 0 | R65: 0 | S65: 0 | T65: 0 | U65: 0 | V65: 0 | W65: 0 | X65: 1 | Y65: None | Z65: Unknown | AA65: Not OfS | AB65: NA | AC65: NA | AD65: No tariff | AE65: No WP Tariff | AF65: No TRAC | AG65: No TEF | AH65: None | AI65: Feb 2021 (Unistats)
A66: 10000894 | B66: 287 | C66: Bristol Baptist College | D66: Bristol Baptist College | E66: Not UCAS | F66: England | G66: South West | H66: BS8 3NJ | I66: -2.625879 | J66: 51.460494 | K66: E06000023 | L66: Bristol, City of | M66: E06000023 | N66: Bristol, City of | O66: Bristol West | P66: Bristol | Q66: 1 | R66: 0 | S66: 0 | T66: 1 | U66: 0 | V66: 0 | W66: 0 | X66: 0 | Y66: No university title | Z66: AP | AA66: Approved | AB66: No | AC66: No | AD66: No tariff | AE66: c | AF66: No TRAC | AG66: Provisional | AH66: None | AI66: 0
A67: 10028216 | B67: 280 | C67: Brit College Limited | D67: Brit College | E67: Not UCAS | F67: England | G67: London | H67: E14 7HS | I67: -0.035142 | J67: 51.512369 | K67: E09000030 | L67: Tower Hamlets | M67: E09000030 | N67: Tower Hamlets | O67: Poplar and Limehouse | P67: London | Q67: 1 | R67: 0 | S67: 0 | T67: 1 | U67: 0 | V67: 0 | W67: 0 | X67: 0 | Y67: No university title | Z67: AP | AA67: Approved | AB67: No | AC67: No | AD67: No tariff | AE67: No WP Tariff | AF67: No TRAC | AG67: Bronze | AH67: None | AI67: 0
A68: 10038772 | B68: 427 | C68: British Academy of Jewellery Limited | D68: British Academy of Jewellery | E68: Not UCAS | F68: England | G68: London | H68: EC1N 8UA | I68: -0.108968 | J68: 51.520487 | K68: E09000007 | L68: Camden | M68: E09000007 | N68: Camden | O68: Holborn and St Pancras | P68: London | Q68: 1 | R68: 0 | S68: 1 | T68: 1 | U68: 0 | V68: 0 | W68: 0 | X68: 0 | Y68: No university title | Z68: Unknown | AA68: Approved (fee cap) | AB68: Yes | AC68: No | AD68: Other providers | AE68: No WP Tariff | AF68: No TRAC | AG68: No TEF | AH68: None | AI68: 0
A69: 10000920 | B69: No INSTID | C69: British Institute of Technology, England | D69: British Institute of Technology | E69: B67 | F69: England | G69: London | H69: E7 9HZ | I69: 0.022695 | J69: 51.545909 | K69: E09000025 | L69: Newham | M69: E09000025 | N69: Newham | O69: West Ham | P69: London | Q69: 0 | R69: 0 | S69: 0 | T69: 0 | U69: 0 | V69: 0 | W69: 0 | X69: 1 | Y69: None | Z69: Unknown | AA69: Not OfS | AB69: NA | AC69: NA | AD69: No tariff | AE69: No WP Tariff | AF69: No TRAC | AG69: No TEF | AH69: None | AI69: 0
A70: 10000944 | B70: 1157 | C70: Brockenhurst College | D70: Brockenhurst College | E70: Not UCAS | F70: England | G70: South East | H70: SO42 7ZE | I70: -1.569931 | J70: 50.821457 | K70: E07000091 | L70: New Forest | M70: E07000091 | N70: New Forest | O70: New Forest East | Q70: 1 | R70: 0 | S70: 0 | T70: 0 | U70: 0 | V70: 0 | W70: 1 | X70: 0 | Y70: FEC | Z70: FEC | AA70: Approved (fee cap) | AB70: Yes | AC70: No | AD70: Further education and sixth form colleges | AE70: No WP Tariff | AF70: No TRAC | AG70: No TEF | AH70: AoC | AI70: 0
A71: 10000948 | B71: 1155 | C71: Bromley College of Further and Higher Education | D71: Bromley College | E71: B97 | F71: England | G71: London | H71: BR2 8HE | I71: 0.034796 | J71: 51.38666 | K71: E09000006 | L71: Bromley | M71: E09000006 | N71: Bromley | O71: Beckenham | P71: London | Q71: 1 | R71: 0 | S71: 0 | T71: 0 | U71: 0 | V71: 0 | W71: 1 | X71: 1 | Y71: FEC | Z71: FEC | AA71: Approved (fee cap) | AB71: Yes | AC71: Yes | AD71: Further education and sixth form colleges | AE71: No WP Tariff | AF71: No TRAC | AG71: Silver | AH71: None | AI71: 0
A72: 10032985 | B72: No INSTID | C72: Bromley Schools Collegiate | D72: Bromley Schools | E72: Not UCAS | F72: England | G72: London | H72: BR7 6HE | I72: 0.089186 | J72: 51.418617 | K72: E09000006 | L72: Bromley | M72: E09000006 | N72: Bromley | O72: Bromley and Chislehurst | P72: London | Q72: 0 | R72: 0 | S72: 0 | T72: 0 | U72: 0 | V72: 0 | W72: 1 | X72: 0 | Y72: None | Z72: Unknown | AA72: Not OfS | AB72: NA | AC72: NA | AD72: No tariff | AE72: No WP Tariff | AF72: No TRAC | AG72: No TEF | AH72: None | AI72: Apr 2021 (SLC)
A73: 10000950 | B73: 1156 | C73: Brooklands College | D73: Brooklands College | E73: B83 | F73: England | G73: South East | H73: KT13 8TT | I73: -0.465522 | J73: 51.362672 | K73: E07000207 | L73: Elmbridge | M73: E07000207 | N73: Elmbridge | O73: Runnymede and Weybridge | Q73: 1 | R73: 0 | S73: 0 | T73: 0 | U73: 0 | V73: 0 | W73: 0 | X73: 1 | Y73: FEC | Z73: FEC | AA73: Approved (fee cap) | AB73: Yes | AC73: Yes | AD73: Further education and sixth form colleges | AE73: No WP Tariff | AF73: No TRAC | AG73: Silver | AH73: AoC | AI73: 0
A74: 10000961 | B74: 113 | C74: Brunel University London | D74: Brunel | E74: B84 | F74: England | G74: London | H74: UB8 3PH | I74: -0.472856 | J74: 51.532838 | K74: E09000017 | L74: Hillingdon | M74: E09000017 | N74: Hillingdon | O74: Uxbridge and South Ruislip | P74: London | Q74: 1 | R74: 0 | S74: 1 | T74: 1 | U74: 0 | V74: 0 | W74: 1 | X74: 1 | Y74: University Title | Z74: HEI | AA74: Approved (fee cap) | AB74: Yes | AC74: Yes | AD74: HEIs with medium scores | AE74: Medium | AF74: B | AG74: Silver | AH74: London Higher | AI74: 0
A75: 10000275 | B75: No INSTID | C75: Buckinghamshire College Group | D75: Buckinghamshire College | E75: A55 | F75: England | G75: South East | H75: HP7 9HN | I75: -0.58945 | J75: 51.668961 | K75: E06000060 | L75: Buckinghamshire | M75: E06000060 | N75: Buckinghamshire | O75: Chesham and Amersham | Q75: 0 | R75: 0 | S75: 0 | T75: 0 | U75: 0 | V75: 0 | W75: 0 | X75: 1 | Y75: None | Z75: Unknown | AA75: Not OfS | AB75: NA | AC75: NA | AD75: No tariff | AE75: No WP Tariff | AF75: No TRAC | AG75: No TEF | AH75: AoC | AI75: 0
A76: 10000975 | B76: 9 | C76: Buckinghamshire New University | D76: Bucks New | E76: B94 | F76: England | G76: South East | H76: HP11 2JZ | I76: -0.752036 | J76: 51.627509 | K76: E06000060 | L76: Buckinghamshire | M76: E06000060 | N76: Buckinghamshire | O76: Wycombe | P76: High Wycombe | Q76: 1 | R76: 0 | S76: 1 | T76: 1 | U76: 0 | V76: 0 | W76: 1 | X76: 1 | Y76: University Title | Z76: HEI | AA76: Approved (fee cap) | AB76: Yes | AC76: Yes | AD76: HEIs with low scores | AE76: Low | AF76: E | AG76: Silver | AH76: GuildHE | AI76: 0
A77: 10001000 | B77: 1152 | C77: Burnley College | D77: Burnley College | E77: B69 | F77: England | G77: North West | H77: BB12 0AN | I77: -2.24807 | J77: 53.793909 | K77: E07000117 | L77: Burnley | M77: E07000117 | N77: Burnley | O77: Burnley | P77: Burnley | Q77: 1 | R77: 0 | S77: 0 | T77: 0 | U77: 0 | V77: 0 | W77: 1 | X77: 1 | Y77: FEC | Z77: FEC | AA77: Approved (fee cap) | AB77: Yes | AC77: Yes | AD77: Further education and sixth form colleges | AE77: No WP Tariff | AF77: No TRAC | AG77: Silver | AH77: AoC | AI77: 0
A78: 10001004 | B78: 1153 | C78: Burton and South Derbyshire College | D78: Burton College | E78: Not UCAS | F78: England | G78: West Midlands | H78: DE14 3RL | I78: -1.631174 | J78: 52.799693 | K78: E07000193 | L78: East Staffordshire | M78: E07000193 | N78: East Staffordshire | O78: Burton | P78: Burton upon Trent | Q78: 1 | R78: 0 | S78: 0 | T78: 0 | U78: 0 | V78: 0 | W78: 0 | X78: 0 | Y78: FEC | Z78: FEC | AA78: Approved (fee cap) | AB78: Yes | AC78: Yes | AD78: Further education and sixth form colleges | AE78: No WP Tariff | AF78: No TRAC | AG78: Silver | AH78: AoC | AI78: 0
A79: 10001005 | B79: 1151 | C79: Bury College | D79: Bury College | E79: B93 | F79: England | G79: North West | H79: BL9 0BG | I79: -2.296091 | J79: 53.587602 | K79: E08000002 | L79: Bury | M79: E08000002 | N79: Bury | O79: Bury North | P79: Bury | Q79: 1 | R79: 0 | S79: 0 | T79: 0 | U79: 0 | V79: 0 | W79: 1 | X79: 1 | Y79: FEC | Z79: FEC | AA79: Approved (fee cap) | AB79: Yes | AC79: Yes | AD79: Further education and sixth form colleges | AE79: No WP Tariff | AF79: No TRAC | AG79: Silver | AH79: AoC | AI79: 0
A80: 10049578 | B80: No INSTID | C80: Cabot Learning Federation Scitt | D80: Cabot Learning Scitt | E80: Not UCAS | F80: England | G80: South West | H80: BS5 9JH | I80: -2.562168 | J80: 51.460196 | K80: E06000023 | L80: Bristol, City of | M80: E06000023 | N80: Bristol, City of | O80: Bristol West | P80: Bristol | Q80: 0 | R80: 0 | S80: 0 | T80: 0 | U80: 0 | V80: 0 | W80: 1 | X80: 0 | Y80: None | Z80: SCITT | AA80: Not OfS | AB80: NA | AC80: NA | AD80: No tariff | AE80: No WP Tariff | AF80: No TRAC | AG80: No TEF | AH80: None | AI80: Feb 2022 (SLC)
A81: 10001093 | B81: 1150 | C81: Calderdale College | D81: Calderdale College | E81: C02 | F81: England | G81: Yorkshire and The Humber | H81: HX1 3UZ | I81: -1.874416 | J81: 53.719527 | K81: E08000033 | L81: Calderdale | M81: E08000033 | N81: Calderdale | O81: Halifax | P81: Halifax | Q81: 1 | R81: 0 | S81: 0 | T81: 0 | U81: 0 | V81: 0 | W81: 1 | X81: 1 | Y81: FEC | Z81: FEC | AA81: Approved (fee cap) | AB81: Yes | AC81: Yes | AD81: Further education and sixth form colleges | AE81: No WP Tariff | AF81: No TRAC | AG81: Silver | AH81: AoC | AI81: 0
A82: 10010308 | B82: 332 | C82: Cambridge Arts & Sciences Limited | D82: Cambridge Arts | E82: C06 | F82: England | G82: East of England | H82: CB5 8AD | I82: 0.1189 | J82: 52.208783 | K82: E07000008 | L82: Cambridge | M82: E07000008 | N82: Cambridge | O82: Cambridge | P82: Cambridge | Q82: 1 | R82: 0 | S82: 0 | T82: 1 | U82: 0 | V82: 0 | W82: 0 | X82: 1 | Y82: No university title | Z82: AP | AA82: Approved | AB82: No | AC82: No | AD82: No tariff | AE82: c | AF82: No TRAC | AG82: No TEF | AH82: None | AI82: 0
A83: 10001116 | B83: 1149 | C83: Cambridge Regional College | D83: Cambridge College | E83: C09 | F83: England | G83: East of England | H83: CB4 2QT | I83: 0.13434 | J83: 52.235278 | K83: E07000012 | L83: South Cambridgeshire | M83: E07000012 | N83: South Cambridgeshire | O83: South East Cambridgeshire | P83: Cambridge | Q83: 1 | R83: 0 | S83: 0 | T83: 0 | U83: 0 | V83: 0 | W83: 1 | X83: 1 | Y83: FEC | Z83: FEC | AA83: Approved (fee cap) | AB83: Yes | AC83: Yes | AD83: Further education and sixth form colleges | AE83: No WP Tariff | AF83: No TRAC | AG83: Bronze | AH83: AoC | AI83: 0
A84: 10055220 | B84: No INSTID | C84: Cambridge Teaching Schools Network Training Par... | D84: Cambridge Teaching Schools | E84: Not UCAS | F84: England | G84: East of England | H84: CB23 7DU | I84: 0.010441 | J84: 52.184735 | K84: E07000012 | L84: South Cambridgeshire | M84: E07000012 | N84: South Cambridgeshire | O84: South Cambridgeshire | Q84: 0 | R84: 0 | S84: 0 | T84: 0 | U84: 0 | V84: 0 | W84: 1 | X84: 0 | Y84: None | Z84: Unknown | AA84: Not OfS | AB84: NA | AC84: NA | AD84: No tariff | AE84: No WP Tariff | AF84: No TRAC | AG84: No TEF | AH84: None | AI84: Apr 2021 (SLC)
A85: 10001143 | B85: 12 | C85: Canterbury Christ Church University | D85: Canterbury Christ | E85: C10 | F85: England | G85: South East | H85: CT1 1QU | I85: 1.089364 | J85: 51.279643 | K85: E07000106 | L85: Canterbury | M85: E07000106 | N85: Canterbury | O85: Canterbury | Q85: 1 | R85: 0 | S85: 1 | T85: 1 | U85: 0 | V85: 0 | W85: 1 | X85: 1 | Y85: University Title | Z85: HEI | AA85: Approved (fee cap) | AB85: Yes | AC85: Yes | AD85: HEIs with low scores | AE85: Low | AF85: E | AG85: Silver | AH85: MillionPlus, Cathedrals Group | AI85: 0
A86: 10034450 | B86: 1199 | C86: Cardiff and Vale College | D86: Cardiff and Vale | E86: Not UCAS | F86: Wales | G86: Wales | H86: CF10 5FE | I86: -3.172884 | J86: 51.469695 | K86: W06000015 | L86: Cardiff | M86: W06000015 | N86: Cardiff | O86: Cardiff South and Penarth | P86: Cardiff | Q86: 0 | R86: 0 | S86: 0 | T86: 0 | U86: 0 | V86: 0 | W86: 0 | X86: 0 | Y86: None | Z86: Unknown | AA86: Not OfS | AB86: NA | AC86: NA | AD86: No tariff | AE86: No WP Tariff | AF86: No TRAC | AG86: No TEF | AH86: None | AI86: Jun 2022 (other)
A87: 10007854 | B87: 89 | C87: Cardiff Metropolitan University | D87: Cardiff Met | E87: C20 | F87: Wales | G87: Wales | H87: CF5 2YB | I87: -3.21211 | J87: 51.495831 | K87: W06000015 | L87: Cardiff | M87: W06000015 | N87: Cardiff | O87: Cardiff West | P87: Cardiff | Q87: 0 | R87: 1 | S87: 1 | T87: 1 | U87: 0 | V87: 0 | W87: 1 | X87: 1 | Y87: None | Z87: HEI | AA87: Not OfS | AB87: NA | AC87: NA | AD87: No tariff | AE87: Medium | AF87: E | AG87: Silver | AH87: None | AI87: 0
A88: 10007814 | B88: 179 | C88: Cardiff University | D88: Cardiff | E88: C15 | F88: Wales | G88: Wales | H88: CF10 3AT | I88: -3.179717 | J88: 51.489014 | K88: W06000015 | L88: Cardiff | M88: W06000015 | N88: Cardiff | O88: Cardiff Central | P88: Cardiff | Q88: 0 | R88: 1 | S88: 1 | T88: 1 | U88: 0 | V88: 0 | W88: 1 | X88: 1 | Y88: None | Z88: HEI | AA88: Not OfS | AB88: NA | AC88: NA | AD88: No tariff | AE88: Medium | AF88: A | AG88: Silver | AH88: Russell Group | AI88: 0
A89: 10001165 | B89: 1147 | C89: Cardinal Newman Catholic Sixth Form College | D89: Cardinal Newman | E89: Not UCAS | F89: England | G89: North West | H89: PR1 4HD | I89: -2.688869 | J89: 53.757096 | K89: E07000123 | L89: Preston | M89: E07000123 | N89: Preston | O89: Preston | P89: Preston | Q89: 1 | R89: 0 | S89: 0 | T89: 0 | U89: 0 | V89: 0 | W89: 1 | X89: 0 | Y89: FEC | Z89: FEC | AA89: Approved | AB89: No | AC89: No | AD89: No tariff | AE89: No WP Tariff | AF89: No TRAC | AG89: Provisional | AH89: AoC | AI89: 0
A90: 10055116 | B90: No INSTID | C90: Carmel Teacher Training Partnership (Cttp) | D90: Carmel Teacher Training | E90: Not UCAS | F90: England | G90: North East | H90: DL3 8RW | I90: -1.585908 | J90: 54.524179 | K90: E06000005 | L90: Darlington | M90: E06000005 | N90: Darlington | O90: Darlington | P90: Darlington | Q90: 0 | R90: 0 | S90: 0 | T90: 0 | U90: 0 | V90: 0 | W90: 1 | X90: 0 | Y90: None | Z90: SCITT | AA90: Not OfS | AB90: NA | AC90: NA | AD90: No tariff | AE90: No WP Tariff | AF90: No TRAC | AG90: No TEF | AH90: None | AI90: Apr 2021 (SLC)
A91: 10002061 | B91: 1146 | C91: Central Bedfordshire College | D91: Central Bedfordshire College | E91: C27 | F91: England | G91: East of England | H91: LU5 4HG | I91: -0.518838 | J91: 51.890763 | K91: E06000056 | L91: Central Bedfordshire | M91: E06000056 | N91: Central Bedfordshire | O91: South West Bedfordshire | Q91: 1 | R91: 0 | S91: 0 | T91: 0 | U91: 0 | V91: 0 | W91: 1 | X91: 1 | Y91: FEC | Z91: FEC | AA91: Approved (fee cap) | AB91: Yes | AC91: Yes | AD91: Further education and sixth form colleges | AE91: No WP Tariff | AF91: No TRAC | AG91: Silver | AH91: AoC | AI91: 0
A92: 10024024 | B92: 409 | C92: Central Film School London Ltd | D92: Central Film | E92: C34 | F92: England | G92: London | H92: E1 7SA | I92: -0.070974 | J92: 51.517082 | K92: E09000030 | L92: Tower Hamlets | M92: E09000030 | N92: Tower Hamlets | O92: Bethnal Green and Bow | P92: London | Q92: 1 | R92: 0 | S92: 1 | T92: 1 | U92: 0 | V92: 0 | W92: 0 | X92: 1 | Y92: No university title | Z92: Unknown | AA92: Approved (fee cap) | AB92: Yes | AC92: Yes | AD92: Other providers | AE92: No WP Tariff | AF92: No TRAC | AG92: Provisional | AH92: None | AI92: 0
A93: 10001264 | B93: No INSTID | C93: Central School of Ballet Charitable Trust Ltd | D93: Central School of Ballet | E93: Not UCAS | F93: England | G93: London | H93: SE1 8DJ | I93: -0.106788 | J93: 51.506389 | K93: E09000028 | L93: Southwark | M93: E09000028 | N93: Southwark | O93: Bermondsey and Old Southwark | P93: London | Q93: 1 | R93: 0 | S93: 0 | T93: 0 | U93: 0 | V93: 0 | W93: 0 | X93: 0 | Y93: No university title | Z93: Unknown | AA93: Approved (fee cap) | AB93: Yes | AC93: Yes | AD93: No tariff | AE93: No WP Tariff | AF93: No TRAC | AG93: No TEF | AH93: None | AI93: Aug 2022 (OfS register)
A94: 10021550 | B94: 1196 | C94: Centre for Alternative Technology | D94: Centre For Alternative Technology | E94: Not UCAS | F94: Wales | G94: Wales | H94: SY20 9AZ | I94: -3.839399 | J94: 52.6238 | K94: W06000023 | L94: Powys | M94: W06000023 | N94: Powys | O94: Montgomeryshire | Q94: 0 | R94: 0 | S94: 0 | T94: 0 | U94: 0 | V94: 0 | W94: 1 | X94: 0 | Y94: None | Z94: Unknown | AA94: Not OfS | AB94: NA | AC94: NA | AD94: No tariff | AE94: No WP Tariff | AF94: No TRAC | AG94: No TEF | AH94: None | AI94: 0
A95: 10005972 | B95: 1142 | C95: Cheshire College South and West | D95: Cheshire College | E95: Not UCAS | F95: England | G95: North West | H95: CW2 8AB | I95: -2.454971 | J95: 53.089011 | K95: E06000049 | L95: Cheshire East | M95: E06000049 | N95: Cheshire East | O95: Crewe and Nantwich | Q95: 1 | R95: 0 | S95: 0 | T95: 0 | U95: 0 | V95: 0 | W95: 1 | X95: 0 | Y95: FEC | Z95: FEC | AA95: Approved (fee cap) | AB95: Yes | AC95: Yes | AD95: Further education and sixth form colleges | AE95: No WP Tariff | AF95: No TRAC | AG95: No TEF | AH95: AoC | AI95: 0
A96: 10001378 | B96: 1144 | C96: Chesterfield College | D96: Chesterfield College | E96: C56 | F96: England | G96: East Midlands | H96: S41 7NG | I96: -1.425048 | J96: 53.240256 | K96: E07000034 | L96: Chesterfield | M96: E07000034 | N96: Chesterfield | O96: Chesterfield | P96: Chesterfield | Q96: 1 | R96: 0 | S96: 0 | T96: 0 | U96: 0 | V96: 0 | W96: 1 | X96: 1 | Y96: FEC | Z96: FEC | AA96: Approved (fee cap) | AB96: Yes | AC96: Yes | AD96: Further education and sixth form colleges | AE96: No WP Tariff | AF96: No TRAC | AG96: Provisional | AH96: AoC | AI96: 0
A97: 10007817 | B97: 1143 | C97: Chichester College Group | D97: Chichester College | E97: C57 | F97: England | G97: South East | H97: PO19 1SB | I97: -0.787766 | J97: 50.83492 | K97: E07000225 | L97: Chichester | M97: E07000225 | N97: Chichester | O97: Chichester | Q97: 1 | R97: 0 | S97: 0 | T97: 0 | U97: 0 | V97: 0 | W97: 1 | X97: 1 | Y97: FEC | Z97: FEC | AA97: Approved (fee cap) | AB97: Yes | AC97: Yes | AD97: Further education and sixth form colleges | AE97: No WP Tariff | AF97: No TRAC | AG97: Silver | AH97: AoC | AI97: 0
A98: 10026921 | B98: 342 | C98: Christ the Redeemer College | D98: Christ the Redeemer College | E98: Not UCAS | F98: England | G98: London | H98: HA2 7LX | I98: -0.370208 | J98: 51.577239 | K98: E09000015 | L98: Harrow | M98: E09000015 | N98: Harrow | O98: Harrow West | P98: London | Q98: 1 | R98: 0 | S98: 0 | T98: 1 | U98: 0 | V98: 0 | W98: 1 | X98: 0 | Y98: No university title | Z98: AP | AA98: Approved | AB98: No | AC98: No | AD98: No tariff | AE98: No WP Tariff | AF98: No TRAC | AG98: No TEF | AH98: GuildHE | AI98: 0
A99: 10001419 | B99: 291 | C99: Christie's Education Limited | D99: Christie’s Education | E99: Not UCAS | F99: England | G99: London | H99: SW1Y 6QT | I99: -0.137601 | J99: 51.506557 | K99: E09000033 | L99: Westminster | M99: E09000033 | N99: Westminster | O99: Cities of London and Westminster | P99: London | Q99: 0 | R99: 0 | S99: 0 | T99: 1 | U99: 0 | V99: 0 | W99: 0 | X99: 0 | Y99: None | Z99: AP | AA99: Not OfS | AB99: NA | AC99: NA | AD99: No tariff | AE99: No WP Tariff | AF99: No TRAC | AG99: No TEF | AH99: None | AI99: 0
A100: 10039082 | B100: 292 | C100: City and Guilds of London Art School Limited | D100: City and Guilds | E100: Not UCAS | F100: England | G100: London | H100: SE11 4DJ | I100: -0.10805 | J100: 51.486707 | K100: E09000022 | L100: Lambeth | M100: E09000022 | N100: Lambeth | O100: Vauxhall | P100: London | Q100: 1 | R100: 0 | S100: 0 | T100: 1 | U100: 0 | V100: 0 | W100: 0 | X100: 0 | Y100: No university title | Z100: AP | AA100: Approved | AB100: No | AC100: No | AD100: No tariff | AE100: c | AF100: No TRAC | AG100: Provisional | AH100: None | AI100: 0
...

Sheet Finance
A1: ﻿Title: | B1: Table 1 - Consolidated statement of comprehensive income and expenditure
A2: Subtitle: | B2: Academic years 2015/16 to 2020/21
A3: Reference ID: | B3: DT031 Table 1
A4: Data source: | B4: HESA / OfS
A5: Data source link: | B5: https://www.hesa.ac.uk/data-and-analysis/finances/table-1
A6: Data file canonical link: | B6: https://www.hesa.ac.uk/data-and-analysis/finances/table-1.csv
A7: Licence: | B7: Creative Commons Attribution 4.0 International Licence
A8: Date: | B8: 2022
A9: Filters: | B9: Country of HE provider | C9: All
B10: Region of HE provider | C10: All
B11: Academic year | C11: 2020/21
B12: Financial Year End | C12: All
A13: Search:
C16: Income (£000s) | D16: Expenditure (£000s)
A17: UKPRN | B17: HE Provider | C17: Financial Year End | D17: Tuition fees and education contracts | E17: Funding body grants | F17: Research grants and contracts | G17: Other income | H17: Investment income | I17: Donations and endowments | J17: Total income | K17: Staff costs | L17: Restructuring costs | M17: Other operating expenses | N17: Depreciation and amortisation | O17: Interest and other finance costs | P17: Total expenditure
A18: 10008071 | B18: AA School of Architecture | C18: 44408 | D18: 19072 | E18: 0 | F18: 0 | G18: 1332 | H18: 2 | I18: 870 | J18: 21276 | K18: 9574 | L18: 0 | M18: 6846 | N18: 393 | O18: 57 | P18: 16870
A19: 10007783 | B19: The University of Aberdeen | C19: 44408 | D19: 74423 | E19: 87577 | F19: 45927 | G19: 25764 | H19: 2012 | I19: 236 | J19: 235939 | K19: 146956 | L19: 0 | M19: 59306 | N19: 16855 | O19: 5840 | P19: 228957
A20: 10007849 | B20: Abertay University | C20: 44408 | D20: 10414 | E20: 21581 | F20: 2862 | G20: 2003 | H20: 313 | I20: 4 | J20: 37177 | K20: 27715 | L20: 0 | M20: 7300 | N20: 2671 | O20: 416 | P20: 38102
A21: 10007856 | B21: Aberystwyth University | C21: 44408 | D21: 53989 | E21: 22054 | F21: 20217 | G21: 21707 | H21: 233 | I21: 642 | J21: 118842 | K21: 66187 | L21: 184 | M21: 38544 | N21: 11946 | O21: 4003 | P21: 120864
A22: 10067853 | B22: ACM Guildford Limited | C22: 44074 | D22: 10614 | E22: 1381 | F22: 0 | G22: 619 | H22: 0 | I22: 0 | J22: 12614 | K22: 5953 | L22: 0 | M22: 3559 | N22: 101 | O22: 18 | P22: 9631
A23: 10000248 | B23: Academy of Live and Recorded Arts | C23: 44074 | D23: 2851 | E23: 0 | F23: 0 | G23: 283 | H23: 32 | I23: 0 | J23: 3166 | K23: 1507 | L23: 0 | M23: 1541 | N23: 85 | O23: 0 | P23: 3133
A24: 10000163 | B24: AECC University College | C24: 44408 | D24: 8064 | E24: 908 | F24: 32 | G24: 1390 | H24: 3 | I24: 38 | J24: 10435 | K24: 6159 | L24: 33 | M24: 2496 | N24: 509 | O24: 90 | P24: 9287
A25: 10032036 | B25: Amity Global Education | C25: 44286 | D25: 462 | E25: 26 | F25: 0 | G25: 644 | H25: 0 | I25: 0 | J25: 1132 | K25: 434 | L25: 0 | M25: 642 | N25: 1 | O25: 0 | P25: 1077
A26: 10000291 | B26: Anglia Ruskin University | C26: 44408 | D26: 230557 | E26: 23071 | F26: 3691 | G26: 11329 | H26: 9 | I26: 217 | J26: 268874 | K26: 109368 | L26: 0 | M26: 142863 | N26: 13279 | O26: 4721 | P26: 270231
A27: 10041898 | B27: Apex College London | C27: 44196 | D27: 642 | E27: 0 | F27: 0 | G27: 0 | H27: 0 | I27: 0 | J27: 642 | K27: 337 | L27: 0 | M27: 265 | N27: 0 | O27: 0 | P27: 602
A28: 10062759 | B28: Applied Business Academy Limited | C28: 44196 | D28: 321 | E28: 0 | F28: 0 | G28: 462 | H28: 0 | I28: 0 | J28: 783 | K28: 469 | L28: 0 | M28: 185 | N28: 32 | O28: 0 | P28: 686
A29: 10005451 | B29: Arden University | C29: 44135 | D29: 33272 | E29: 1985 | F29: 0 | G29: 1023 | H29: 564 | I29: 0 | J29: 36844 | K29: 16794 | L29: 0 | M29: 17646 | N29: 1142 | O29: 0 | P29: 35582
... A291: 10007167 | B291: The University of York | C291: 44408 | D291: 229082 | E291: 47471 | F291: 69810 | G291: 63351 | H291: 908 | I291: 3230 | J291: 413852 | K291: 246124 | L291: 0 | M291: 133947 | N291: 32334 | O291: 10276 | P291: 422681
B292: Year to date total | D292: 23462674 | E292: 6005301 | F292: 6561033 | G292: 6827826 | H292: 330833 | I292: 834262 | J292: 44021929 | K292: 23630712 | L292: 99592 | M292: 14890666 | N292: 2963640 | O292: 794166 | P292: 42378776

Sheet Students
A1: ﻿Title: | B1: Table 1 - HE student enrolments by HE provider
A2: Subtitle: | B2: Academic years 2014/15 to 2020/21
A3: Reference ID: | B3: DT051 Table 1
A4: Data source: | B4: HESA
A5: Data source link: | B5: https://www.hesa.ac.uk/data-and-analysis/students/table-1
A6: Data file canonical link: | B6: https://www.hesa.ac.uk/data-and-analysis/students/table-1.csv
A7: Licence: | B7: Creative Commons Attribution 4.0 International Licence
A8: Date: | B8: 2022
A9: Filters: | B9: Country of HE provider | C9: All
B10: Region of HE provider | C10: All
B11: First year marker | C11: All
B12: Level of study | C12: All
B13: Mode of study | C13: All
B14: Academic year | C14: 2020/21
A15: Search:
A18: UKPRN | B18: HE provider | C18: Female | D18: Male | E18: Other | F18: Not known | G18: Total
A19: 10008071 | B19: AA School of Architecture | C19: 575 | D19: 390 | E19: 0 | F19: 0 | G19: 965
A20: 10007783 | B20: The University of Aberdeen | C20: 9300 | D20: 6750 | E20: 30 | F20: 0 | G20: 16080
A21: 10007849 | B21: Abertay University | C21: 2180 | D21: 2385 | E21: 10 | F21: 0 | G21: 4575
A22: 10007856 | B22: Aberystwyth University | C22: 4385 | D22: 3535 | E22: 120 | F22: 0 | G22: 8040
A23: 10067853 | B23: ACM Guildford Limited | C23: 375 | D23: 790 | E23: 20 | F23: 0 | G23: 1185
A24: 10000248 | B24: Academy of Live and Recorded Arts | C24: 145 | D24: 125 | E24: 0 | F24: 0 | G24: 270
A25: 10000163 | B25: AECC University College | C25: 400 | D25: 475 | E25: 0 | F25: 0 | G25: 875
A26: 10032036 | B26: Amity Global Education | C26: 40 | D26: 40 | E26: 0 | F26: 0 | G26: 80
A27: 10000291 | B27: Anglia Ruskin University | C27: 20010 | D27: 12150 | E27: 20 | F27: 0 | G27: 32180
A28: 10041898 | B28: Apex College London | C28: 125 | D28: 45 | E28: 0 | F28: 0 | G28: 170
A29: 10062759 | B29: Applied Business Academy Limited | C29: 80 | D29: 140 | E29: 0 | F29: 0 | G29: 220
A30: 10005451 | B30: Arden University | C30: 7340 | D30: 4420 | E30: 0 | F30: 0 | G30: 11760
... A300: 10007167 | B300: The University of York | C300: 12615 | D300: 10050 | E300: 30 | F300: 0 | G300: 22695
B301: Total | C301: 1568795 | D301: 1177525 | E301: 5505 | F301: 35 | G301: 2751865
